pepe/__init__.py
pepe/__version__.py
pepe/main.py
pepe/py.typed
py_pepe-0.0.5.dist-info/entry_points.txt
py_pepe-0.0.5.dist-info/WHEEL
py_pepe-0.0.5.dist-info/METADATA
py_pepe-0.0.5.dist-info/licenses/LICENSE
py_pepe-0.0.5.dist-info/RECORD
